cdef_cohort_builder/__init__.py
cdef_cohort_builder/__main__.py
cdef_cohort_builder/_version.py
cdef_cohort_builder/logging_config.py
cdef_cohort_builder/main.py
cdef_cohort_builder/mapping_utils.py
cdef_cohort_builder/population.py
cdef_cohort_builder/settings.py
cdef_cohort_builder/events/plotting.py
cdef_cohort_builder/events/summaries.py
cdef_cohort_builder/functions/check_parquet.py
cdef_cohort_builder/functions/population_summary.py
cdef_cohort_builder/mappings/beskst13.json
cdef_cohort_builder/mappings/civst.json
cdef_cohort_builder/mappings/fm_mark.json
cdef_cohort_builder/mappings/hustype.json
cdef_cohort_builder/mappings/icd10.json
cdef_cohort_builder/mappings/isced.json
cdef_cohort_builder/mappings/jobkat.json
cdef_cohort_builder/mappings/plads.json
cdef_cohort_builder/mappings/pre_socio.json
cdef_cohort_builder/mappings/reg.json
cdef_cohort_builder/mappings/scd.json
cdef_cohort_builder/mappings/socio13.json
cdef_cohort_builder/mappings/statsb.json
cdef_cohort_builder/mappings/tilknyt.json
cdef_cohort_builder/registers/__init__.py
cdef_cohort_builder/registers/akm.py
cdef_cohort_builder/registers/bef.py
cdef_cohort_builder/registers/generic.py
cdef_cohort_builder/registers/idan.py
cdef_cohort_builder/registers/ind.py
cdef_cohort_builder/registers/longitudinal.py
cdef_cohort_builder/registers/lpr3_diagnoser.py
cdef_cohort_builder/registers/lpr3_kontakter.py
cdef_cohort_builder/registers/lpr_adm.py
cdef_cohort_builder/registers/lpr_bes.py
cdef_cohort_builder/registers/lpr_diag.py
cdef_cohort_builder/registers/uddf.py
cdef_cohort_builder/utils/__init__.py
cdef_cohort_builder/utils/columns.py
cdef_cohort_builder/utils/config.py
cdef_cohort_builder/utils/date.py
cdef_cohort_builder/utils/event.py
cdef_cohort_builder/utils/harmonize_lpr.py
cdef_cohort_builder/utils/hash_utils.py
cdef_cohort_builder/utils/icd.py
cdef_cohort_builder/utils/isced.py
cdef_cohort_builder/utils/logging_decorator.py
cdef_cohort_builder/utils/mappings.py
cdef_cohort_builder-0.5.0.dist-info/METADATA
cdef_cohort_builder-0.5.0.dist-info/WHEEL
cdef_cohort_builder-0.5.0.dist-info/entry_points.txt
cdef_cohort_builder-0.5.0.dist-info/licenses/LICENSE.txt
cdef_cohort_builder-0.5.0.dist-info/RECORD
